{"nodes": [{"id": "home_deckard_schedaprodark_backend_app_ocr_adapter_py", "label": "ocr_adapter.py", "file_type": "code", "source_file": "backend/app/ocr_adapter.py", "source_location": "L1"}, {"id": "app_ocr_adapter_ocradapter", "label": "OcrAdapter", "file_type": "code", "source_file": "backend/app/ocr_adapter.py", "source_location": "L11"}, {"id": "abc", "label": "ABC", "file_type": "code", "source_file": "", "source_location": ""}, {"id": "app_ocr_adapter_ocradapter_extract", "label": ".extract()", "file_type": "code", "source_file": "backend/app/ocr_adapter.py", "source_location": "L17"}, {"id": "ocrinput", "label": "OcrInput", "file_type": "code", "source_file": "", "source_location": ""}, {"id": "ocrresult", "label": "OcrResult", "file_type": "code", "source_file": "", "source_location": ""}, {"id": "app_ocr_adapter_textonlyocradapter", "label": "TextOnlyOcrAdapter", "file_type": "code", "source_file": "backend/app/ocr_adapter.py", "source_location": "L21"}, {"id": "app_ocr_adapter_textonlyocradapter_extract", "label": ".extract()", "file_type": "code", "source_file": "backend/app/ocr_adapter.py", "source_location": "L31"}, {"id": "app_ocr_adapter_pypdfadapter", "label": "PypdfAdapter", "file_type": "code", "source_file": "backend/app/ocr_adapter.py", "source_location": "L67"}, {"id": "app_ocr_adapter_pypdfadapter_extract", "label": ".extract()", "file_type": "code", "source_file": "backend/app/ocr_adapter.py", "source_location": "L76"}, {"id": "app_ocr_adapter_pptxadapter", "label": "PptxAdapter", "file_type": "code", "source_file": "backend/app/ocr_adapter.py", "source_location": "L114"}, {"id": "app_ocr_adapter_pptxadapter_extract", "label": ".extract()", "file_type": "code", "source_file": "backend/app/ocr_adapter.py", "source_location": "L119"}, {"id": "app_ocr_adapter_xlsxadapter", "label": "XlsxAdapter", "file_type": "code", "source_file": "backend/app/ocr_adapter.py", "source_location": "L175"}, {"id": "app_ocr_adapter_xlsxadapter_extract", "label": ".extract()", "file_type": "code", "source_file": "backend/app/ocr_adapter.py", "source_location": "L180"}, {"id": "app_ocr_adapter_mistralocradapter", "label": "MistralOcrAdapter", "file_type": "code", "source_file": "backend/app/ocr_adapter.py", "source_location": "L230"}, {"id": "app_ocr_adapter_mistralocradapter_extract", "label": ".extract()", "file_type": "code", "source_file": "backend/app/ocr_adapter.py", "source_location": "L239"}, {"id": "app_ocr_adapter_rationale_12", "label": "Stable boundary between case analysis and replaceable OCR engines.", "file_type": "rationale", "source_file": "backend/app/ocr_adapter.py", "source_location": "L12"}, {"id": "app_ocr_adapter_rationale_18", "label": "Return normalized OCR text, page refs, confidence, and warnings.", "file_type": "rationale", "source_file": "backend/app/ocr_adapter.py", "source_location": "L18"}, {"id": "app_ocr_adapter_rationale_22", "label": "Alpha contract stub.      This intentionally does not run OCR. It only passes th", "file_type": "rationale", "source_file": "backend/app/ocr_adapter.py", "source_location": "L22"}, {"id": "app_ocr_adapter_rationale_68", "label": "Extract text from native (non-scanned) PDFs using pypdf \u2014 free, instant, local.", "file_type": "rationale", "source_file": "backend/app/ocr_adapter.py", "source_location": "L68"}, {"id": "app_ocr_adapter_rationale_115", "label": "Extract text from PPTX files using python-pptx.", "file_type": "rationale", "source_file": "backend/app/ocr_adapter.py", "source_location": "L115"}, {"id": "app_ocr_adapter_rationale_176", "label": "Extract text from XLSX files using openpyxl.", "file_type": "rationale", "source_file": "backend/app/ocr_adapter.py", "source_location": "L176"}, {"id": "app_ocr_adapter_rationale_231", "label": "OCR via Mistral OCR API (mistral-ocr-latest).      Handles scanned PDFs and imag", "file_type": "rationale", "source_file": "backend/app/ocr_adapter.py", "source_location": "L231"}], "edges": [{"source": "home_deckard_schedaprodark_backend_app_ocr_adapter_py", "target": "base64", "relation": "imports", "context": "import", "confidence": "EXTRACTED", "source_file": "backend/app/ocr_adapter.py", "source_location": "L3", "weight": 1.0}, {"source": "home_deckard_schedaprodark_backend_app_ocr_adapter_py", "target": "io", "relation": "imports", "context": "import", "confidence": "EXTRACTED", "source_file": "backend/app/ocr_adapter.py", "source_location": "L4", "weight": 1.0}, {"source": "home_deckard_schedaprodark_backend_app_ocr_adapter_py", "target": "os", "relation": "imports", "context": "import", "confidence": "EXTRACTED", "source_file": "backend/app/ocr_adapter.py", "source_location": "L5", "weight": 1.0}, {"source": "home_deckard_schedaprodark_backend_app_ocr_adapter_py", "target": "abc", "relation": "imports_from", "context": "import", "confidence": "EXTRACTED", "source_file": "backend/app/ocr_adapter.py", "source_location": "L6", "weight": 1.0}, {"source": "home_deckard_schedaprodark_backend_app_ocr_adapter_py", "target": "home_deckard_schedaprodark_backend_app_ocr_models_py", "relation": "imports_from", "context": "import", "confidence": "EXTRACTED", "source_file": "backend/app/ocr_adapter.py", "source_location": "L8", "weight": 1.0}, {"source": "home_deckard_schedaprodark_backend_app_ocr_adapter_py", "target": "app_ocr_adapter_ocradapter", "relation": "contains", "confidence": "EXTRACTED", "source_file": "backend/app/ocr_adapter.py", "source_location": "L11", "weight": 1.0}, {"source": "app_ocr_adapter_ocradapter", "target": "abc", "relation": "inherits", "confidence": "EXTRACTED", "source_file": "backend/app/ocr_adapter.py", "source_location": "L11", "weight": 1.0}, {"source": "app_ocr_adapter_ocradapter", "target": "app_ocr_adapter_ocradapter_extract", "relation": "method", "confidence": "EXTRACTED", "source_file": "backend/app/ocr_adapter.py", "source_location": "L17", "weight": 1.0}, {"source": "app_ocr_adapter_ocradapter_extract", "target": "ocrinput", "relation": "references", "context": "parameter_type", "confidence": "EXTRACTED", "source_file": "backend/app/ocr_adapter.py", "source_location": "L17", "weight": 1.0}, {"source": "app_ocr_adapter_ocradapter_extract", "target": "ocrresult", "relation": "references", "context": "return_type", "confidence": "EXTRACTED", "source_file": "backend/app/ocr_adapter.py", "source_location": "L17", "weight": 1.0}, {"source": "home_deckard_schedaprodark_backend_app_ocr_adapter_py", "target": "app_ocr_adapter_textonlyocradapter", "relation": "contains", "confidence": "EXTRACTED", "source_file": "backend/app/ocr_adapter.py", "source_location": "L21", "weight": 1.0}, {"source": "app_ocr_adapter_textonlyocradapter", "target": "app_ocr_adapter_ocradapter", "relation": "inherits", "confidence": "EXTRACTED", "source_file": "backend/app/ocr_adapter.py", "source_location": "L21", "weight": 1.0}, {"source": "app_ocr_adapter_textonlyocradapter", "target": "app_ocr_adapter_textonlyocradapter_extract", "relation": "method", "confidence": "EXTRACTED", "source_file": "backend/app/ocr_adapter.py", "source_location": "L31", "weight": 1.0}, {"source": "app_ocr_adapter_textonlyocradapter_extract", "target": "ocrinput", "relation": "references", "context": "parameter_type", "confidence": "EXTRACTED", "source_file": "backend/app/ocr_adapter.py", "source_location": "L31", "weight": 1.0}, {"source": "app_ocr_adapter_textonlyocradapter_extract", "target": "ocrresult", "relation": "references", "context": "return_type", "confidence": "EXTRACTED", "source_file": "backend/app/ocr_adapter.py", "source_location": "L31", "weight": 1.0}, {"source": "home_deckard_schedaprodark_backend_app_ocr_adapter_py", "target": "app_ocr_adapter_pypdfadapter", "relation": "contains", "confidence": "EXTRACTED", "source_file": "backend/app/ocr_adapter.py", "source_location": "L67", "weight": 1.0}, {"source": "app_ocr_adapter_pypdfadapter", "target": "app_ocr_adapter_ocradapter", "relation": "inherits", "confidence": "EXTRACTED", "source_file": "backend/app/ocr_adapter.py", "source_location": "L67", "weight": 1.0}, {"source": "app_ocr_adapter_pypdfadapter", "target": "app_ocr_adapter_pypdfadapter_extract", "relation": "method", "confidence": "EXTRACTED", "source_file": "backend/app/ocr_adapter.py", "source_location": "L76", "weight": 1.0}, {"source": "app_ocr_adapter_pypdfadapter_extract", "target": "ocrinput", "relation": "references", "context": "parameter_type", "confidence": "EXTRACTED", "source_file": "backend/app/ocr_adapter.py", "source_location": "L76", "weight": 1.0}, {"source": "app_ocr_adapter_pypdfadapter_extract", "target": "ocrresult", "relation": "references", "context": "return_type", "confidence": "EXTRACTED", "source_file": "backend/app/ocr_adapter.py", "source_location": "L76", "weight": 1.0}, {"source": "home_deckard_schedaprodark_backend_app_ocr_adapter_py", "target": "app_ocr_adapter_pptxadapter", "relation": "contains", "confidence": "EXTRACTED", "source_file": "backend/app/ocr_adapter.py", "source_location": "L114", "weight": 1.0}, {"source": "app_ocr_adapter_pptxadapter", "target": "app_ocr_adapter_ocradapter", "relation": "inherits", "confidence": "EXTRACTED", "source_file": "backend/app/ocr_adapter.py", "source_location": "L114", "weight": 1.0}, {"source": "app_ocr_adapter_pptxadapter", "target": "app_ocr_adapter_pptxadapter_extract", "relation": "method", "confidence": "EXTRACTED", "source_file": "backend/app/ocr_adapter.py", "source_location": "L119", "weight": 1.0}, {"source": "app_ocr_adapter_pptxadapter_extract", "target": "ocrinput", "relation": "references", "context": "parameter_type", "confidence": "EXTRACTED", "source_file": "backend/app/ocr_adapter.py", "source_location": "L119", "weight": 1.0}, {"source": "app_ocr_adapter_pptxadapter_extract", "target": "ocrresult", "relation": "references", "context": "return_type", "confidence": "EXTRACTED", "source_file": "backend/app/ocr_adapter.py", "source_location": "L119", "weight": 1.0}, {"source": "home_deckard_schedaprodark_backend_app_ocr_adapter_py", "target": "app_ocr_adapter_xlsxadapter", "relation": "contains", "confidence": "EXTRACTED", "source_file": "backend/app/ocr_adapter.py", "source_location": "L175", "weight": 1.0}, {"source": "app_ocr_adapter_xlsxadapter", "target": "app_ocr_adapter_ocradapter", "relation": "inherits", "confidence": "EXTRACTED", "source_file": "backend/app/ocr_adapter.py", "source_location": "L175", "weight": 1.0}, {"source": "app_ocr_adapter_xlsxadapter", "target": "app_ocr_adapter_xlsxadapter_extract", "relation": "method", "confidence": "EXTRACTED", "source_file": "backend/app/ocr_adapter.py", "source_location": "L180", "weight": 1.0}, {"source": "app_ocr_adapter_xlsxadapter_extract", "target": "ocrinput", "relation": "references", "context": "parameter_type", "confidence": "EXTRACTED", "source_file": "backend/app/ocr_adapter.py", "source_location": "L180", "weight": 1.0}, {"source": "app_ocr_adapter_xlsxadapter_extract", "target": "ocrresult", "relation": "references", "context": "return_type", "confidence": "EXTRACTED", "source_file": "backend/app/ocr_adapter.py", "source_location": "L180", "weight": 1.0}, {"source": "home_deckard_schedaprodark_backend_app_ocr_adapter_py", "target": "app_ocr_adapter_mistralocradapter", "relation": "contains", "confidence": "EXTRACTED", "source_file": "backend/app/ocr_adapter.py", "source_location": "L230", "weight": 1.0}, {"source": "app_ocr_adapter_mistralocradapter", "target": "app_ocr_adapter_ocradapter", "relation": "inherits", "confidence": "EXTRACTED", "source_file": "backend/app/ocr_adapter.py", "source_location": "L230", "weight": 1.0}, {"source": "app_ocr_adapter_mistralocradapter", "target": "app_ocr_adapter_mistralocradapter_extract", "relation": "method", "confidence": "EXTRACTED", "source_file": "backend/app/ocr_adapter.py", "source_location": "L239", "weight": 1.0}, {"source": "app_ocr_adapter_mistralocradapter_extract", "target": "ocrinput", "relation": "references", "context": "parameter_type", "confidence": "EXTRACTED", "source_file": "backend/app/ocr_adapter.py", "source_location": "L239", "weight": 1.0}, {"source": "app_ocr_adapter_mistralocradapter_extract", "target": "ocrresult", "relation": "references", "context": "return_type", "confidence": "EXTRACTED", "source_file": "backend/app/ocr_adapter.py", "source_location": "L239", "weight": 1.0}, {"source": "app_ocr_adapter_textonlyocradapter_extract", "target": "ocrresult", "relation": "calls", "context": "call", "confidence": "EXTRACTED", "source_file": "backend/app/ocr_adapter.py", "source_location": "L33", "weight": 1.0}, {"source": "app_ocr_adapter_pypdfadapter_extract", "target": "ocrresult", "relation": "calls", "context": "call", "confidence": "EXTRACTED", "source_file": "backend/app/ocr_adapter.py", "source_location": "L78", "weight": 1.0}, {"source": "app_ocr_adapter_pptxadapter_extract", "target": "ocrresult", "relation": "calls", "context": "call", "confidence": "EXTRACTED", "source_file": "backend/app/ocr_adapter.py", "source_location": "L125", "weight": 1.0}, {"source": "app_ocr_adapter_xlsxadapter_extract", "target": "ocrresult", "relation": "calls", "context": "call", "confidence": "EXTRACTED", "source_file": "backend/app/ocr_adapter.py", "source_location": "L186", "weight": 1.0}, {"source": "app_ocr_adapter_mistralocradapter_extract", "target": "ocrresult", "relation": "calls", "context": "call", "confidence": "EXTRACTED", "source_file": "backend/app/ocr_adapter.py", "source_location": "L242", "weight": 1.0}, {"source": "app_ocr_adapter_rationale_12", "target": "app_ocr_adapter_ocradapter", "relation": "rationale_for", "confidence": "EXTRACTED", "source_file": "backend/app/ocr_adapter.py", "source_location": "L12", "weight": 1.0}, {"source": "app_ocr_adapter_rationale_18", "target": "app_ocr_adapter_ocradapter_extract", "relation": "rationale_for", "confidence": "EXTRACTED", "source_file": "backend/app/ocr_adapter.py", "source_location": "L18", "weight": 1.0}, {"source": "app_ocr_adapter_rationale_22", "target": "app_ocr_adapter_textonlyocradapter", "relation": "rationale_for", "confidence": "EXTRACTED", "source_file": "backend/app/ocr_adapter.py", "source_location": "L22", "weight": 1.0}, {"source": "app_ocr_adapter_rationale_68", "target": "app_ocr_adapter_pypdfadapter", "relation": "rationale_for", "confidence": "EXTRACTED", "source_file": "backend/app/ocr_adapter.py", "source_location": "L68", "weight": 1.0}, {"source": "app_ocr_adapter_rationale_115", "target": "app_ocr_adapter_pptxadapter", "relation": "rationale_for", "confidence": "EXTRACTED", "source_file": "backend/app/ocr_adapter.py", "source_location": "L115", "weight": 1.0}, {"source": "app_ocr_adapter_rationale_176", "target": "app_ocr_adapter_xlsxadapter", "relation": "rationale_for", "confidence": "EXTRACTED", "source_file": "backend/app/ocr_adapter.py", "source_location": "L176", "weight": 1.0}, {"source": "app_ocr_adapter_rationale_231", "target": "app_ocr_adapter_mistralocradapter", "relation": "rationale_for", "confidence": "EXTRACTED", "source_file": "backend/app/ocr_adapter.py", "source_location": "L231", "weight": 1.0}], "raw_calls": [{"caller_nid": "app_ocr_adapter_textonlyocradapter_extract", "callee": "OcrWarning", "is_member_call": false, "source_file": "/home/deckard/schedaprodark/backend/app/ocr_adapter.py", "source_location": "L38", "receiver": null}, {"caller_nid": "app_ocr_adapter_textonlyocradapter_extract", "callee": "read_bytes", "is_member_call": true, "source_file": "/home/deckard/schedaprodark/backend/app/ocr_adapter.py", "source_location": "L50", "receiver": null}, {"caller_nid": "app_ocr_adapter_textonlyocradapter_extract", "callee": "decode", "is_member_call": true, "source_file": "/home/deckard/schedaprodark/backend/app/ocr_adapter.py", "source_location": "L52", "receiver": null}, {"caller_nid": "app_ocr_adapter_textonlyocradapter_extract", "callee": "OcrPage", "is_member_call": false, "source_file": "/home/deckard/schedaprodark/backend/app/ocr_adapter.py", "source_location": "L56", "receiver": null}, {"caller_nid": "app_ocr_adapter_textonlyocradapter_extract", "callee": "OcrWarning", "is_member_call": false, "source_file": "/home/deckard/schedaprodark/backend/app/ocr_adapter.py", "source_location": "L58", "receiver": null}, {"caller_nid": "app_ocr_adapter_pypdfadapter_extract", "callee": "OcrWarning", "is_member_call": false, "source_file": "/home/deckard/schedaprodark/backend/app/ocr_adapter.py", "source_location": "L80", "receiver": null}, {"caller_nid": "app_ocr_adapter_pypdfadapter_extract", "callee": "OcrWarning", "is_member_call": false, "source_file": "/home/deckard/schedaprodark/backend/app/ocr_adapter.py", "source_location": "L88", "receiver": null}, {"caller_nid": "app_ocr_adapter_pypdfadapter_extract", "callee": "read_bytes", "is_member_call": true, "source_file": "/home/deckard/schedaprodark/backend/app/ocr_adapter.py", "source_location": "L93", "receiver": null}, {"caller_nid": "app_ocr_adapter_pypdfadapter_extract", "callee": "OcrWarning", "is_member_call": false, "source_file": "/home/deckard/schedaprodark/backend/app/ocr_adapter.py", "source_location": "L96", "receiver": null}, {"caller_nid": "app_ocr_adapter_pypdfadapter_extract", "callee": "PdfReader", "is_member_call": true, "source_file": "/home/deckard/schedaprodark/backend/app/ocr_adapter.py", "source_location": "L98", "receiver": "pypdf"}, {"caller_nid": "app_ocr_adapter_pypdfadapter_extract", "callee": "BytesIO", "is_member_call": true, "source_file": "/home/deckard/schedaprodark/backend/app/ocr_adapter.py", "source_location": "L98", "receiver": "io"}, {"caller_nid": "app_ocr_adapter_pypdfadapter_extract", "callee": "strip", "is_member_call": true, "source_file": "/home/deckard/schedaprodark/backend/app/ocr_adapter.py", "source_location": "L101", "receiver": null}, {"caller_nid": "app_ocr_adapter_pypdfadapter_extract", "callee": "extract_text", "is_member_call": true, "source_file": "/home/deckard/schedaprodark/backend/app/ocr_adapter.py", "source_location": "L101", "receiver": "page"}, {"caller_nid": "app_ocr_adapter_pypdfadapter_extract", "callee": "append", "is_member_call": true, "source_file": "/home/deckard/schedaprodark/backend/app/ocr_adapter.py", "source_location": "L103", "receiver": "pages"}, {"caller_nid": "app_ocr_adapter_pypdfadapter_extract", "callee": "OcrPage", "is_member_call": false, "source_file": "/home/deckard/schedaprodark/backend/app/ocr_adapter.py", "source_location": "L103", "receiver": null}, {"caller_nid": "app_ocr_adapter_pypdfadapter_extract", "callee": "OcrWarning", "is_member_call": false, "source_file": "/home/deckard/schedaprodark/backend/app/ocr_adapter.py", "source_location": "L108", "receiver": null}, {"caller_nid": "app_ocr_adapter_pptxadapter_extract", "callee": "endswith", "is_member_call": true, "source_file": "/home/deckard/schedaprodark/backend/app/ocr_adapter.py", "source_location": "L124", "receiver": null}, {"caller_nid": "app_ocr_adapter_pptxadapter_extract", "callee": "OcrWarning", "is_member_call": false, "source_file": "/home/deckard/schedaprodark/backend/app/ocr_adapter.py", "source_location": "L127", "receiver": null}, {"caller_nid": "app_ocr_adapter_pptxadapter_extract", "callee": "OcrWarning", "is_member_call": false, "source_file": "/home/deckard/schedaprodark/backend/app/ocr_adapter.py", "source_location": "L135", "receiver": null}, {"caller_nid": "app_ocr_adapter_pptxadapter_extract", "callee": "read_bytes", "is_member_call": true, "source_file": "/home/deckard/schedaprodark/backend/app/ocr_adapter.py", "source_location": "L140", "receiver": null}, {"caller_nid": "app_ocr_adapter_pptxadapter_extract", "callee": "OcrWarning", "is_member_call": false, "source_file": "/home/deckard/schedaprodark/backend/app/ocr_adapter.py", "source_location": "L143", "receiver": null}, {"caller_nid": "app_ocr_adapter_pptxadapter_extract", "callee": "Presentation", "is_member_call": false, "source_file": "/home/deckard/schedaprodark/backend/app/ocr_adapter.py", "source_location": "L145", "receiver": null}, {"caller_nid": "app_ocr_adapter_pptxadapter_extract", "callee": "BytesIO", "is_member_call": true, "source_file": "/home/deckard/schedaprodark/backend/app/ocr_adapter.py", "source_location": "L145", "receiver": "io"}, {"caller_nid": "app_ocr_adapter_pptxadapter_extract", "callee": "strip", "is_member_call": true, "source_file": "/home/deckard/schedaprodark/backend/app/ocr_adapter.py", "source_location": "L152", "receiver": null}, {"caller_nid": "app_ocr_adapter_pptxadapter_extract", "callee": "append", "is_member_call": true, "source_file": "/home/deckard/schedaprodark/backend/app/ocr_adapter.py", "source_location": "L154", "receiver": "texts"}, {"caller_nid": "app_ocr_adapter_pptxadapter_extract", "callee": "strip", "is_member_call": true, "source_file": "/home/deckard/schedaprodark/backend/app/ocr_adapter.py", "source_location": "L158", "receiver": null}, {"caller_nid": "app_ocr_adapter_pptxadapter_extract", "callee": "append", "is_member_call": true, "source_file": "/home/deckard/schedaprodark/backend/app/ocr_adapter.py", "source_location": "L160", "receiver": "texts"}, {"caller_nid": "app_ocr_adapter_pptxadapter_extract", "callee": "append", "is_member_call": true, "source_file": "/home/deckard/schedaprodark/backend/app/ocr_adapter.py", "source_location": "L162", "receiver": "texts"}, {"caller_nid": "app_ocr_adapter_pptxadapter_extract", "callee": "append", "is_member_call": true, "source_file": "/home/deckard/schedaprodark/backend/app/ocr_adapter.py", "source_location": "L164", "receiver": "pages"}, {"caller_nid": "app_ocr_adapter_pptxadapter_extract", "callee": "OcrPage", "is_member_call": false, "source_file": "/home/deckard/schedaprodark/backend/app/ocr_adapter.py", "source_location": "L164", "receiver": null}, {"caller_nid": "app_ocr_adapter_pptxadapter_extract", "callee": "join", "is_member_call": true, "source_file": "/home/deckard/schedaprodark/backend/app/ocr_adapter.py", "source_location": "L164", "receiver": null}, {"caller_nid": "app_ocr_adapter_pptxadapter_extract", "callee": "OcrWarning", "is_member_call": false, "source_file": "/home/deckard/schedaprodark/backend/app/ocr_adapter.py", "source_location": "L169", "receiver": null}, {"caller_nid": "app_ocr_adapter_xlsxadapter_extract", "callee": "endswith", "is_member_call": true, "source_file": "/home/deckard/schedaprodark/backend/app/ocr_adapter.py", "source_location": "L185", "receiver": null}, {"caller_nid": "app_ocr_adapter_xlsxadapter_extract", "callee": "OcrWarning", "is_member_call": false, "source_file": "/home/deckard/schedaprodark/backend/app/ocr_adapter.py", "source_location": "L188", "receiver": null}, {"caller_nid": "app_ocr_adapter_xlsxadapter_extract", "callee": "OcrWarning", "is_member_call": false, "source_file": "/home/deckard/schedaprodark/backend/app/ocr_adapter.py", "source_location": "L196", "receiver": null}, {"caller_nid": "app_ocr_adapter_xlsxadapter_extract", "callee": "read_bytes", "is_member_call": true, "source_file": "/home/deckard/schedaprodark/backend/app/ocr_adapter.py", "source_location": "L201", "receiver": null}, {"caller_nid": "app_ocr_adapter_xlsxadapter_extract", "callee": "OcrWarning", "is_member_call": false, "source_file": "/home/deckard/schedaprodark/backend/app/ocr_adapter.py", "source_location": "L204", "receiver": null}, {"caller_nid": "app_ocr_adapter_xlsxadapter_extract", "callee": "load_workbook", "is_member_call": true, "source_file": "/home/deckard/schedaprodark/backend/app/ocr_adapter.py", "source_location": "L206", "receiver": "openpyxl"}, {"caller_nid": "app_ocr_adapter_xlsxadapter_extract", "callee": "BytesIO", "is_member_call": true, "source_file": "/home/deckard/schedaprodark/backend/app/ocr_adapter.py", "source_location": "L206", "receiver": "io"}, {"caller_nid": "app_ocr_adapter_xlsxadapter_extract", "callee": "iter_rows", "is_member_call": true, "source_file": "/home/deckard/schedaprodark/backend/app/ocr_adapter.py", "source_location": "L211", "receiver": "ws"}, {"caller_nid": "app_ocr_adapter_xlsxadapter_extract", "callee": "strip", "is_member_call": true, "source_file": "/home/deckard/schedaprodark/backend/app/ocr_adapter.py", "source_location": "L212", "receiver": null}, {"caller_nid": "app_ocr_adapter_xlsxadapter_extract", "callee": "strip", "is_member_call": true, "source_file": "/home/deckard/schedaprodark/backend/app/ocr_adapter.py", "source_location": "L212", "receiver": null}, {"caller_nid": "app_ocr_adapter_xlsxadapter_extract", "callee": "append", "is_member_call": true, "source_file": "/home/deckard/schedaprodark/backend/app/ocr_adapter.py", "source_location": "L214", "receiver": "rows_text"}, {"caller_nid": "app_ocr_adapter_xlsxadapter_extract", "callee": "join", "is_member_call": true, "source_file": "/home/deckard/schedaprodark/backend/app/ocr_adapter.py", "source_location": "L214", "receiver": null}, {"caller_nid": "app_ocr_adapter_xlsxadapter_extract", "callee": "append", "is_member_call": true, "source_file": "/home/deckard/schedaprodark/backend/app/ocr_adapter.py", "source_location": "L217", "receiver": "pages"}, {"caller_nid": "app_ocr_adapter_xlsxadapter_extract", "callee": "OcrPage", "is_member_call": false, "source_file": "/home/deckard/schedaprodark/backend/app/ocr_adapter.py", "source_location": "L217", "receiver": null}, {"caller_nid": "app_ocr_adapter_xlsxadapter_extract", "callee": "join", "is_member_call": true, "source_file": "/home/deckard/schedaprodark/backend/app/ocr_adapter.py", "source_location": "L217", "receiver": null}, {"caller_nid": "app_ocr_adapter_xlsxadapter_extract", "callee": "close", "is_member_call": true, "source_file": "/home/deckard/schedaprodark/backend/app/ocr_adapter.py", "source_location": "L219", "receiver": "wb"}, {"caller_nid": "app_ocr_adapter_xlsxadapter_extract", "callee": "OcrWarning", "is_member_call": false, "source_file": "/home/deckard/schedaprodark/backend/app/ocr_adapter.py", "source_location": "L224", "receiver": null}, {"caller_nid": "app_ocr_adapter_mistralocradapter_extract", "callee": "get", "is_member_call": true, "source_file": "/home/deckard/schedaprodark/backend/app/ocr_adapter.py", "source_location": "L240", "receiver": null}, {"caller_nid": "app_ocr_adapter_mistralocradapter_extract", "callee": "OcrWarning", "is_member_call": false, "source_file": "/home/deckard/schedaprodark/backend/app/ocr_adapter.py", "source_location": "L244", "receiver": null}, {"caller_nid": "app_ocr_adapter_mistralocradapter_extract", "callee": "OcrWarning", "is_member_call": false, "source_file": "/home/deckard/schedaprodark/backend/app/ocr_adapter.py", "source_location": "L252", "receiver": null}, {"caller_nid": "app_ocr_adapter_mistralocradapter_extract", "callee": "read_bytes", "is_member_call": true, "source_file": "/home/deckard/schedaprodark/backend/app/ocr_adapter.py", "source_location": "L257", "receiver": null}, {"caller_nid": "app_ocr_adapter_mistralocradapter_extract", "callee": "OcrWarning", "is_member_call": false, "source_file": "/home/deckard/schedaprodark/backend/app/ocr_adapter.py", "source_location": "L260", "receiver": null}, {"caller_nid": "app_ocr_adapter_mistralocradapter_extract", "callee": "decode", "is_member_call": true, "source_file": "/home/deckard/schedaprodark/backend/app/ocr_adapter.py", "source_location": "L264", "receiver": null}, {"caller_nid": "app_ocr_adapter_mistralocradapter_extract", "callee": "standard_b64encode", "is_member_call": true, "source_file": "/home/deckard/schedaprodark/backend/app/ocr_adapter.py", "source_location": "L264", "receiver": "base64"}, {"caller_nid": "app_ocr_adapter_mistralocradapter_extract", "callee": "Mistral", "is_member_call": false, "source_file": "/home/deckard/schedaprodark/backend/app/ocr_adapter.py", "source_location": "L267", "receiver": null}, {"caller_nid": "app_ocr_adapter_mistralocradapter_extract", "callee": "process", "is_member_call": true, "source_file": "/home/deckard/schedaprodark/backend/app/ocr_adapter.py", "source_location": "L268", "receiver": null}, {"caller_nid": "app_ocr_adapter_mistralocradapter_extract", "callee": "strip", "is_member_call": true, "source_file": "/home/deckard/schedaprodark/backend/app/ocr_adapter.py", "source_location": "L275", "receiver": null}, {"caller_nid": "app_ocr_adapter_mistralocradapter_extract", "callee": "append", "is_member_call": true, "source_file": "/home/deckard/schedaprodark/backend/app/ocr_adapter.py", "source_location": "L277", "receiver": "pages"}, {"caller_nid": "app_ocr_adapter_mistralocradapter_extract", "callee": "OcrPage", "is_member_call": false, "source_file": "/home/deckard/schedaprodark/backend/app/ocr_adapter.py", "source_location": "L277", "receiver": null}, {"caller_nid": "app_ocr_adapter_mistralocradapter_extract", "callee": "OcrWarning", "is_member_call": false, "source_file": "/home/deckard/schedaprodark/backend/app/ocr_adapter.py", "source_location": "L281", "receiver": null}]}